openfisk/__init__.py
openfisk/nl/__init__.py
openfisk/nl/asset/__init__.py
openfisk/nl/asset/calculate_asset_tax.py
openfisk/nl/asset/test__calculate_asset_tax.py
openfisk/nl/income/__init__.py
openfisk/nl/income/calculate_income_tax.py
openfisk/nl/income/test__calculate_income_tax.py
openfisk-0.1.0.dist-info/LICENSE
openfisk-0.1.0.dist-info/METADATA
openfisk-0.1.0.dist-info/WHEEL
openfisk-0.1.0.dist-info/RECORD
