Metadata-Version: 2.1
Name: openfisk
Version: 0.1.0
Summary: OpenFisk is an open-source Python library that collects functions for tax-related calculations.
Author: Thijs Franck
Author-email: thijsfranck@gmail.com
Requires-Python: >=3.12,<4.0
Classifier: Programming Language :: Python :: 3
Classifier: Programming Language :: Python :: 3.12
Requires-Dist: numpy (>=1.26,<2.0)
